Workbook

Sheet Dados de Vendas
A1: Produtos | B1: Regiao | C1: Qtde | D1: Valor Unitário | E1: Valor da venda | F1: Data | G1: Mês (MONTH) | H1: Ano (YEAR) | I1: Mês e Ano | J1: Dia da Semana | K1: Fabricante | L1: Gerente | M1: Supervisor | N1: Gerente2 | O1: Código de Barras | P1: Frete | Q1: META MAIOR R$ 500,00 | R1: META - QUANTIDADE MAIOR 300 unid | S1: ALGUMA META FOI ATINGIDA? FÓRMULA "OU" (OR) | T1: AS DUAS METAS FORAM ATINGIDAS? FÓRMULA "E" ("AND") | U1: FRETE NA PROMOÇÃO | V1: COMISSÃO - BASE 1 | W1: COMISSÃO BASE 2 | X1: COMISSÃO BASE 1
A2: Dorflex | B2: CENTRO-OESTE | C2: 500 | D2: 1.5 | E2: =C2*D2 -> 750 | F2: 40975 | G2: =TEXT(F2,"mmmm") -> março | H2: =YEAR(F2) -> 2012 | I2: =G2&"/"&H2 -> março/2012 | J2: =TEXT(F2,"dddd") -> quarta-feira | K2: =VLOOKUP(A2,RELACIONAMENTOS!A:C,2,0) -> ATOTAL | L2: =VLOOKUP(A2,RELACIONAMENTOS!A:C,3,0) -> Simone | M2: =VLOOKUP(B2,RELACIONAMENTOS!E:F,2,0) -> João | N2: =VLOOKUP(B2,RELACIONAMENTOS!H:I,2,0) -> Daniel | O2: =VLOOKUP(A2,RELACIONAMENTOS!K:L,2,0) -> 78912345678 | P2: =VLOOKUP(B2,RELACIONAMENTOS!N:O,2,0) -> 90 | Q2: =IF(E2>500,"Meta atingida","Não atingida") -> Meta atingida | R2: =IF(C2>300,"Meta atingida","Não atingida") -> Meta atingida | S2: =IF(OR(Q2="Meta atingida",R2="Meta atingida"), "Sim","Não") -> Sim | T2: =IF(AND(Q2="Meta atingida",R2="Meta atingida"), "Sim","Não") -> Sim | U2: =IF(E2>=500,0,VLOOKUP(B2,RELACIONAMENTOS!N:O,2,0)) -> 0 | V2: =IF(E2<=200,1%,IF(E2<=400,2%,IF(E2<=600,3%,IF(E2<=800,4%,IF(E2<=1000,5%,IF(E2<=1800,10%,15%)))))) -> 0.04 | W2: =VLOOKUP(E2,RELACIONAMENTOS!$Q$1:$S$11,3,1) -> 0.04 | Z2: TESTE (teste_lógico) | AB2: Resultado | AD2: TESTE - FORMATAÇÃO CONDICIONAL
A3: Dorflex | B3: CENTRO-OESTE | C3: 20 | D3: 3 | E3: =C3*D3 -> 60 | F3: 40974 | G3: =TEXT(F3,"mmmm") -> março | H3: =YEAR(F3) -> 2012 | I3: =G3&"/"&H3 -> março/2012 | J3: =TEXT(F3,"dddd") -> terça-feira | K3: =VLOOKUP(A3,RELACIONAMENTOS!A:C,2,0) -> ATOTAL | L3: =VLOOKUP(A3,RELACIONAMENTOS!A:C,3,0) -> Simone | M3: =VLOOKUP(B3,RELACIONAMENTOS!E:F,2,0) -> João | N3: =VLOOKUP(B3,RELACIONAMENTOS!H:I,2,0) -> Daniel | O3: =VLOOKUP(A3,RELACIONAMENTOS!K:L,2,0) -> 78912345678 | P3: =VLOOKUP(B3,RELACIONAMENTOS!N:O,2,0) -> 90 | Q3: =IF(E3>500,"Meta atingida","Não atingida") -> Não atingida | R3: =IF(C3>300,"Meta atingida","Não atingida") -> Não atingida | S3: =IF(OR(Q3="Meta atingida",R3="Meta atingida"), "Sim","Não") -> Não | T3: =IF(AND(Q3="Meta atingida",R3="Meta atingida"), "Sim","Não") -> Não | U3: =IF(E3>=500,0,VLOOKUP(B3,RELACIONAMENTOS!N:O,2,0)) -> 90 | V3: =IF(E3<=200,1%,IF(E3<=400,2%,IF(E3<=600,3%,IF(E3<=800,4%,IF(E3<=1000,5%,IF(E3<=1800,10%,15%)))))) -> 0.01 | W3: =VLOOKUP(E3,RELACIONAMENTOS!$Q$1:$S$11,3,1) -> 0.01 | Z3: 1=1 | AA3: Um é igual a um? | AB3: TRUE
A4: Dorflex | B4: CENTRO-OESTE | C4: 20 | D4: 3 | E4: =C4*D4 -> 60 | F4: 40973 | G4: =TEXT(F4,"mmmm") -> março | H4: =YEAR(F4) -> 2012 | I4: =G4&"/"&H4 -> março/2012 | J4: =TEXT(F4,"dddd") -> segunda-feira | K4: =VLOOKUP(A4,RELACIONAMENTOS!A:C,2,0) -> ATOTAL | L4: =VLOOKUP(A4,RELACIONAMENTOS!A:C,3,0) -> Simone | M4: =VLOOKUP(B4,RELACIONAMENTOS!E:F,2,0) -> João | N4: =VLOOKUP(B4,RELACIONAMENTOS!H:I,2,0) -> Daniel | O4: =VLOOKUP(A4,RELACIONAMENTOS!K:L,2,0) -> 78912345678 | P4: =VLOOKUP(B4,RELACIONAMENTOS!N:O,2,0) -> 90 | Q4: =IF(E4>500,"Meta atingida","Não atingida") -> Não atingida | R4: =IF(C4>300,"Meta atingida","Não atingida") -> Não atingida | S4: =IF(OR(Q4="Meta atingida",R4="Meta atingida"), "Sim","Não") -> Não | T4: =IF(AND(Q4="Meta atingida",R4="Meta atingida"), "Sim","Não") -> Não | U4: =IF(E4>=500,0,VLOOKUP(B4,RELACIONAMENTOS!N:O,2,0)) -> 90 | V4: =IF(E4<=200,1%,IF(E4<=400,2%,IF(E4<=600,3%,IF(E4<=800,4%,IF(E4<=1000,5%,IF(E4<=1800,10%,15%)))))) -> 0.01 | W4: =VLOOKUP(E4,RELACIONAMENTOS!$Q$1:$S$11,3,1) -> 0.01 | Z4: 1>1 | AA4: Um é maior que um? | AB4: FALSE
A5: Dorflex | B5: CENTRO-OESTE | C5: 10 | D5: 3 | E5: =C5*D5 -> 30 | F5: 40972 | G5: =TEXT(F5,"mmmm") -> março | H5: =YEAR(F5) -> 2012 | I5: =G5&"/"&H5 -> março/2012 | J5: =TEXT(F5,"dddd") -> domingo | K5: =VLOOKUP(A5,RELACIONAMENTOS!A:C,2,0) -> ATOTAL | L5: =VLOOKUP(A5,RELACIONAMENTOS!A:C,3,0) -> Simone | M5: =VLOOKUP(B5,RELACIONAMENTOS!E:F,2,0) -> João | N5: =VLOOKUP(B5,RELACIONAMENTOS!H:I,2,0) -> Daniel | O5: =VLOOKUP(A5,RELACIONAMENTOS!K:L,2,0) -> 78912345678 | P5: =VLOOKUP(B5,RELACIONAMENTOS!N:O,2,0) -> 90 | Q5: =IF(E5>500,"Meta atingida","Não atingida") -> Não atingida | R5: =IF(C5>300,"Meta atingida","Não atingida") -> Não atingida | S5: =IF(OR(Q5="Meta atingida",R5="Meta atingida"), "Sim","Não") -> Não | T5: =IF(AND(Q5="Meta atingida",R5="Meta atingida"), "Sim","Não") -> Não | U5: =IF(E5>=500,0,VLOOKUP(B5,RELACIONAMENTOS!N:O,2,0)) -> 90 | V5: =IF(E5<=200,1%,IF(E5<=400,2%,IF(E5<=600,3%,IF(E5<=800,4%,IF(E5<=1000,5%,IF(E5<=1800,10%,15%)))))) -> 0.01 | W5: =VLOOKUP(E5,RELACIONAMENTOS!$Q$1:$S$11,3,1) -> 0.01 | Z5: 1<1 | AA5: Um é menor que um? | AB5: FALSE
A6: Dorflex | B6: CENTRO-OESTE | C6: 100 | D6: 1.5 | E6: =C6*D6 -> 150 | F6: 40971 | G6: =TEXT(F6,"mmmm") -> março | H6: =YEAR(F6) -> 2012 | I6: =G6&"/"&H6 -> março/2012 | J6: =TEXT(F6,"dddd") -> sábado | K6: =VLOOKUP(A6,RELACIONAMENTOS!A:C,2,0) -> ATOTAL | L6: =VLOOKUP(A6,RELACIONAMENTOS!A:C,3,0) -> Simone | M6: =VLOOKUP(B6,RELACIONAMENTOS!E:F,2,0) -> João | N6: =VLOOKUP(B6,RELACIONAMENTOS!H:I,2,0) -> Daniel | O6: =VLOOKUP(A6,RELACIONAMENTOS!K:L,2,0) -> 78912345678 | P6: =VLOOKUP(B6,RELACIONAMENTOS!N:O,2,0) -> 90 | Q6: =IF(E6>500,"Meta atingida","Não atingida") -> Não atingida | R6: =IF(C6>300,"Meta atingida","Não atingida") -> Não atingida | S6: =IF(OR(Q6="Meta atingida",R6="Meta atingida"), "Sim","Não") -> Não | T6: =IF(AND(Q6="Meta atingida",R6="Meta atingida"), "Sim","Não") -> Não | U6: =IF(E6>=500,0,VLOOKUP(B6,RELACIONAMENTOS!N:O,2,0)) -> 90 | V6: =IF(E6<=200,1%,IF(E6<=400,2%,IF(E6<=600,3%,IF(E6<=800,4%,IF(E6<=1000,5%,IF(E6<=1800,10%,15%)))))) -> 0.01 | W6: =VLOOKUP(E6,RELACIONAMENTOS!$Q$1:$S$11,3,1) -> 0.01 | Z6: 1>=1 | AA6: Um é maior ou igual a um? | AB6: TRUE
A7: Dorflex | B7: CENTRO-OESTE | C7: 300 | D7: 3.5 | E7: =C7*D7 -> 1050 | F7: 40970 | G7: =TEXT(F7,"mmmm") -> março | H7: =YEAR(F7) -> 2012 | I7: =G7&"/"&H7 -> março/2012 | J7: =TEXT(F7,"dddd") -> sexta-feira | K7: =VLOOKUP(A7,RELACIONAMENTOS!A:C,2,0) -> ATOTAL | L7: =VLOOKUP(A7,RELACIONAMENTOS!A:C,3,0) -> Simone | M7: =VLOOKUP(B7,RELACIONAMENTOS!E:F,2,0) -> João | N7: =VLOOKUP(B7,RELACIONAMENTOS!H:I,2,0) -> Daniel | O7: =VLOOKUP(A7,RELACIONAMENTOS!K:L,2,0) -> 78912345678 | P7: =VLOOKUP(B7,RELACIONAMENTOS!N:O,2,0) -> 90 | Q7: =IF(E7>500,"Meta atingida","Não atingida") -> Meta atingida | R7: =IF(C7>300,"Meta atingida","Não atingida") -> Não atingida | S7: =IF(OR(Q7="Meta atingida",R7="Meta atingida"), "Sim","Não") -> Sim | T7: =IF(AND(Q7="Meta atingida",R7="Meta atingida"), "Sim","Não") -> Não | U7: =IF(E7>=500,0,VLOOKUP(B7,RELACIONAMENTOS!N:O,2,0)) -> 0 | V7: =IF(E7<=200,1%,IF(E7<=400,2%,IF(E7<=600,3%,IF(E7<=800,4%,IF(E7<=1000,5%,IF(E7<=1800,10%,15%)))))) -> 0.1 | W7: =VLOOKUP(E7,RELACIONAMENTOS!$Q$1:$S$11,3,1) -> 0.06 | Z7: 1<=1 | AA7: Um é menor ou igual a um? | AB7: TRUE
A8: Dorflex | B8: CENTRO-OESTE | C8: 300 | D8: 3.5 | E8: =C8*D8 -> 1050 | F8: 40969 | G8: =TEXT(F8,"mmmm") -> março | H8: =YEAR(F8) -> 2012 | I8: =G8&"/"&H8 -> março/2012 | J8: =TEXT(F8,"dddd") -> quinta-feira | K8: =VLOOKUP(A8,RELACIONAMENTOS!A:C,2,0) -> ATOTAL | L8: =VLOOKUP(A8,RELACIONAMENTOS!A:C,3,0) -> Simone | M8: =VLOOKUP(B8,RELACIONAMENTOS!E:F,2,0) -> João | N8: =VLOOKUP(B8,RELACIONAMENTOS!H:I,2,0) -> Daniel | O8: =VLOOKUP(A8,RELACIONAMENTOS!K:L,2,0) -> 78912345678 | P8: =VLOOKUP(B8,RELACIONAMENTOS!N:O,2,0) -> 90 | Q8: =IF(E8>500,"Meta atingida","Não atingida") -> Meta atingida | R8: =IF(C8>300,"Meta atingida","Não atingida") -> Não atingida | S8: =IF(OR(Q8="Meta atingida",R8="Meta atingida"), "Sim","Não") -> Sim | T8: =IF(AND(Q8="Meta atingida",R8="Meta atingida"), "Sim","Não") -> Não | U8: =IF(E8>=500,0,VLOOKUP(B8,RELACIONAMENTOS!N:O,2,0)) -> 0 | V8: =IF(E8<=200,1%,IF(E8<=400,2%,IF(E8<=600,3%,IF(E8<=800,4%,IF(E8<=1000,5%,IF(E8<=1800,10%,15%)))))) -> 0.1 | W8: =VLOOKUP(E8,RELACIONAMENTOS!$Q$1:$S$11,3,1) -> 0.06 | Z8: 1<>1 | AA8: Um é diferente de um? | AB8: FALSE
A9: Dorflex | B9: CENTRO-OESTE | C9: 102 | D9: 1.5 | E9: =C9*D9 -> 153 | F9: 40968 | G9: =TEXT(F9,"mmmm") -> fevereiro | H9: =YEAR(F9) -> 2012 | I9: =G9&"/"&H9 -> fevereiro/2012 | J9: =TEXT(F9,"dddd") -> quarta-feira | K9: =VLOOKUP(A9,RELACIONAMENTOS!A:C,2,0) -> ATOTAL | L9: =VLOOKUP(A9,RELACIONAMENTOS!A:C,3,0) -> Simone | M9: =VLOOKUP(B9,RELACIONAMENTOS!E:F,2,0) -> João | N9: =VLOOKUP(B9,RELACIONAMENTOS!H:I,2,0) -> Daniel | O9: =VLOOKUP(A9,RELACIONAMENTOS!K:L,2,0) -> 78912345678 | P9: =VLOOKUP(B9,RELACIONAMENTOS!N:O,2,0) -> 90 | Q9: =IF(E9>500,"Meta atingida","Não atingida") -> Não atingida | R9: =IF(C9>300,"Meta atingida","Não atingida") -> Não atingida | S9: =IF(OR(Q9="Meta atingida",R9="Meta atingida"), "Sim","Não") -> Não | T9: =IF(AND(Q9="Meta atingida",R9="Meta atingida"), "Sim","Não") -> Não | U9: =IF(E9>=500,0,VLOOKUP(B9,RELACIONAMENTOS!N:O,2,0)) -> 90 | V9: =IF(E9<=200,1%,IF(E9<=400,2%,IF(E9<=600,3%,IF(E9<=800,4%,IF(E9<=1000,5%,IF(E9<=1800,10%,15%)))))) -> 0.01 | W9: =VLOOKUP(E9,RELACIONAMENTOS!$Q$1:$S$11,3,1) -> 0.01
A10: Dorflex | B10: CENTRO-OESTE | C10: 102 | D10: 1.5 | E10: =C10*D10 -> 153 | F10: 40967 | G10: =TEXT(F10,"mmmm") -> fevereiro | H10: =YEAR(F10) -> 2012 | I10: =G10&"/"&H10 -> fevereiro/2012 | J10: =TEXT(F10,"dddd") -> terça-feira | K10: =VLOOKUP(A10,RELACIONAMENTOS!A:C,2,0) -> ATOTAL | L10: =VLOOKUP(A10,RELACIONAMENTOS!A:C,3,0) -> Simone | M10: =VLOOKUP(B10,RELACIONAMENTOS!E:F,2,0) -> João | N10: =VLOOKUP(B10,RELACIONAMENTOS!H:I,2,0) -> Daniel | O10: =VLOOKUP(A10,RELACIONAMENTOS!K:L,2,0) -> 78912345678 | P10: =VLOOKUP(B10,RELACIONAMENTOS!N:O,2,0) -> 90 | Q10: =IF(E10>500,"Meta atingida","Não atingida") -> Não atingida | R10: =IF(C10>300,"Meta atingida","Não atingida") -> Não atingida | S10: =IF(OR(Q10="Meta atingida",R10="Meta atingida"), "Sim","Não") -> Não | T10: =IF(AND(Q10="Meta atingida",R10="Meta atingida"), "Sim","Não") -> Não | U10: =IF(E10>=500,0,VLOOKUP(B10,RELACIONAMENTOS!N:O,2,0)) -> 90 | V10: =IF(E10<=200,1%,IF(E10<=400,2%,IF(E10<=600,3%,IF(E10<=800,4%,IF(E10<=1000,5%,IF(E10<=1800,10%,15%)))))) -> 0.01 | W10: =VLOOKUP(E10,RELACIONAMENTOS!$Q$1:$S$11,3,1) -> 0.01
A11: Dorflex | B11: CENTRO-OESTE | C11: 300 | D11: 3 | E11: =C11*D11 -> 900 | F11: 40966 | G11: =TEXT(F11,"mmmm") -> fevereiro | H11: =YEAR(F11) -> 2012 | I11: =G11&"/"&H11 -> fevereiro/2012 | J11: =TEXT(F11,"dddd") -> segunda-feira | K11: =VLOOKUP(A11,RELACIONAMENTOS!A:C,2,0) -> ATOTAL | L11: =VLOOKUP(A11,RELACIONAMENTOS!A:C,3,0) -> Simone | M11: =VLOOKUP(B11,RELACIONAMENTOS!E:F,2,0) -> João | N11: =VLOOKUP(B11,RELACIONAMENTOS!H:I,2,0) -> Daniel | O11: =VLOOKUP(A11,RELACIONAMENTOS!K:L,2,0) -> 78912345678 | P11: =VLOOKUP(B11,RELACIONAMENTOS!N:O,2,0) -> 90 | Q11: =IF(E11>500,"Meta atingida","Não atingida") -> Meta atingida | R11: =IF(C11>300,"Meta atingida","Não atingida") -> Não atingida | S11: =IF(OR(Q11="Meta atingida",R11="Meta atingida"), "Sim","Não") -> Sim | T11: =IF(AND(Q11="Meta atingida",R11="Meta atingida"), "Sim","Não") -> Não | U11: =IF(E11>=500,0,VLOOKUP(B11,RELACIONAMENTOS!N:O,2,0)) -> 0 | V11: =IF(E11<=200,1%,IF(E11<=400,2%,IF(E11<=600,3%,IF(E11<=800,4%,IF(E11<=1000,5%,IF(E11<=1800,10%,15%)))))) -> 0.05 | W11: =VLOOKUP(E11,RELACIONAMENTOS!$Q$1:$S$11,3,1) -> 0.05
A12: Dorflex | B12: CENTRO-OESTE | C12: 344 | D12: 3 | E12: =C12*D12 -> 1032 | F12: 40965 | G12: =TEXT(F12,"mmmm") -> fevereiro | H12: =YEAR(F12) -> 2012 | I12: =G12&"/"&H12 -> fevereiro/2012 | J12: =TEXT(F12,"dddd") -> domingo | K12: =VLOOKUP(A12,RELACIONAMENTOS!A:C,2,0) -> ATOTAL | L12: =VLOOKUP(A12,RELACIONAMENTOS!A:C,3,0) -> Simone | M12: =VLOOKUP(B12,RELACIONAMENTOS!E:F,2,0) -> João | N12: =VLOOKUP(B12,RELACIONAMENTOS!H:I,2,0) -> Daniel | O12: =VLOOKUP(A12,RELACIONAMENTOS!K:L,2,0) -> 78912345678 | P12: =VLOOKUP(B12,RELACIONAMENTOS!N:O,2,0) -> 90 | Q12: =IF(E12>500,"Meta atingida","Não atingida") -> Meta atingida | R12: =IF(C12>300,"Meta atingida","Não atingida") -> Meta atingida | S12: =IF(OR(Q12="Meta atingida",R12="Meta atingida"), "Sim","Não") -> Sim | T12: =IF(AND(Q12="Meta atingida",R12="Meta atingida"), "Sim","Não") -> Sim | U12: =IF(E12>=500,0,VLOOKUP(B12,RELACIONAMENTOS!N:O,2,0)) -> 0 | V12: =IF(E12<=200,1%,IF(E12<=400,2%,IF(E12<=600,3%,IF(E12<=800,4%,IF(E12<=1000,5%,IF(E12<=1800,10%,15%)))))) -> 0.1 | W12: =VLOOKUP(E12,RELACIONAMENTOS!$Q$1:$S$11,3,1) -> 0.06
A13: Dorflex | B13: CENTRO-OESTE | C13: 100 | D13: 3.5 | E13: =C13*D13 -> 350 | F13: 40964 | G13: =TEXT(F13,"mmmm") -> fevereiro | H13: =YEAR(F13) -> 2012 | I13: =G13&"/"&H13 -> fevereiro/2012 | J13: =TEXT(F13,"dddd") -> sábado | K13: =VLOOKUP(A13,RELACIONAMENTOS!A:C,2,0) -> ATOTAL | L13: =VLOOKUP(A13,RELACIONAMENTOS!A:C,3,0) -> Simone | M13: =VLOOKUP(B13,RELACIONAMENTOS!E:F,2,0) -> João | N13: =VLOOKUP(B13,RELACIONAMENTOS!H:I,2,0) -> Daniel | O13: =VLOOKUP(A13,RELACIONAMENTOS!K:L,2,0) -> 78912345678 | P13: =VLOOKUP(B13,RELACIONAMENTOS!N:O,2,0) -> 90 | Q13: =IF(E13>500,"Meta atingida","Não atingida") -> Não atingida | R13: =IF(C13>300,"Meta atingida","Não atingida") -> Não atingida | S13: =IF(OR(Q13="Meta atingida",R13="Meta atingida"), "Sim","Não") -> Não | T13: =IF(AND(Q13="Meta atingida",R13="Meta atingida"), "Sim","Não") -> Não | U13: =IF(E13>=500,0,VLOOKUP(B13,RELACIONAMENTOS!N:O,2,0)) -> 90 | V13: =IF(E13<=200,1%,IF(E13<=400,2%,IF(E13<=600,3%,IF(E13<=800,4%,IF(E13<=1000,5%,IF(E13<=1800,10%,15%)))))) -> 0.02 | W13: =VLOOKUP(E13,RELACIONAMENTOS!$Q$1:$S$11,3,1) -> 0.02
A14: Dorflex | B14: CENTRO-OESTE | C14: 203 | D14: 3.5 | E14: =C14*D14 -> 710.5 | F14: 40963 | G14: =TEXT(F14,"mmmm") -> fevereiro | H14: =YEAR(F14) -> 2012 | I14: =G14&"/"&H14 -> fevereiro/2012 | J14: =TEXT(F14,"dddd") -> sexta-feira | K14: =VLOOKUP(A14,RELACIONAMENTOS!A:C,2,0) -> ATOTAL | L14: =VLOOKUP(A14,RELACIONAMENTOS!A:C,3,0) -> Simone | M14: =VLOOKUP(B14,RELACIONAMENTOS!E:F,2,0) -> João | N14: =VLOOKUP(B14,RELACIONAMENTOS!H:I,2,0) -> Daniel | O14: =VLOOKUP(A14,RELACIONAMENTOS!K:L,2,0) -> 78912345678 | P14: =VLOOKUP(B14,RELACIONAMENTOS!N:O,2,0) -> 90 | Q14: =IF(E14>500,"Meta atingida","Não atingida") -> Meta atingida | R14: =IF(C14>300,"Meta atingida","Não atingida") -> Não atingida | S14: =IF(OR(Q14="Meta atingida",R14="Meta atingida"), "Sim","Não") -> Sim | T14: =IF(AND(Q14="Meta atingida",R14="Meta atingida"), "Sim","Não") -> Não | U14: =IF(E14>=500,0,VLOOKUP(B14,RELACIONAMENTOS!N:O,2,0)) -> 0 | V14: =IF(E14<=200,1%,IF(E14<=400,2%,IF(E14<=600,3%,IF(E14<=800,4%,IF(E14<=1000,5%,IF(E14<=1800,10%,15%)))))) -> 0.04 | W14: =VLOOKUP(E14,RELACIONAMENTOS!$Q$1:$S$11,3,1) -> 0.04
A15: Dorflex | B15: CENTRO-OESTE | C15: 100 | D15: 3.5 | E15: =C15*D15 -> 350 | F15: 40962 | G15: =TEXT(F15,"mmmm") -> fevereiro | H15: =YEAR(F15) -> 2012 | I15: =G15&"/"&H15 -> fevereiro/2012 | J15: =TEXT(F15,"dddd") -> quinta-feira | K15: =VLOOKUP(A15,RELACIONAMENTOS!A:C,2,0) -> ATOTAL | L15: =VLOOKUP(A15,RELACIONAMENTOS!A:C,3,0) -> Simone | M15: =VLOOKUP(B15,RELACIONAMENTOS!E:F,2,0) -> João | N15: =VLOOKUP(B15,RELACIONAMENTOS!H:I,2,0) -> Daniel | O15: =VLOOKUP(A15,RELACIONAMENTOS!K:L,2,0) -> 78912345678 | P15: =VLOOKUP(B15,RELACIONAMENTOS!N:O,2,0) -> 90 | Q15: =IF(E15>500,"Meta atingida","Não atingida") -> Não atingida | R15: =IF(C15>300,"Meta atingida","Não atingida") -> Não atingida | S15: =IF(OR(Q15="Meta atingida",R15="Meta atingida"), "Sim","Não") -> Não | T15: =IF(AND(Q15="Meta atingida",R15="Meta atingida"), "Sim","Não") -> Não | U15: =IF(E15>=500,0,VLOOKUP(B15,RELACIONAMENTOS!N:O,2,0)) -> 90 | V15: =IF(E15<=200,1%,IF(E15<=400,2%,IF(E15<=600,3%,IF(E15<=800,4%,IF(E15<=1000,5%,IF(E15<=1800,10%,15%)))))) -> 0.02 | W15: =VLOOKUP(E15,RELACIONAMENTOS!$Q$1:$S$11,3,1) -> 0.02
A16: Dorflex | B16: CENTRO-OESTE | C16: 100 | D16: 3.5 | E16: =C16*D16 -> 350 | F16: 40961 | G16: =TEXT(F16,"mmmm") -> fevereiro | H16: =YEAR(F16) -> 2012 | I16: =G16&"/"&H16 -> fevereiro/2012 | J16: =TEXT(F16,"dddd") -> quarta-feira | K16: =VLOOKUP(A16,RELACIONAMENTOS!A:C,2,0) -> ATOTAL | L16: =VLOOKUP(A16,RELACIONAMENTOS!A:C,3,0) -> Simone | M16: =VLOOKUP(B16,RELACIONAMENTOS!E:F,2,0) -> João | N16: =VLOOKUP(B16,RELACIONAMENTOS!H:I,2,0) -> Daniel | O16: =VLOOKUP(A16,RELACIONAMENTOS!K:L,2,0) -> 78912345678 | P16: =VLOOKUP(B16,RELACIONAMENTOS!N:O,2,0) -> 90 | Q16: =IF(E16>500,"Meta atingida","Não atingida") -> Não atingida | R16: =IF(C16>300,"Meta atingida","Não atingida") -> Não atingida | S16: =IF(OR(Q16="Meta atingida",R16="Meta atingida"), "Sim","Não") -> Não | T16: =IF(AND(Q16="Meta atingida",R16="Meta atingida"), "Sim","Não") -> Não | U16: =IF(E16>=500,0,VLOOKUP(B16,RELACIONAMENTOS!N:O,2,0)) -> 90 | V16: =IF(E16<=200,1%,IF(E16<=400,2%,IF(E16<=600,3%,IF(E16<=800,4%,IF(E16<=1000,5%,IF(E16<=1800,10%,15%)))))) -> 0.02 | W16: =VLOOKUP(E16,RELACIONAMENTOS!$Q$1:$S$11,3,1) -> 0.02
A17: Dorflex | B17: CENTRO-OESTE | C17: 100 | D17: 3.5 | E17: =C17*D17 -> 350 | F17: 40960 | G17: =TEXT(F17,"mmmm") -> fevereiro | H17: =YEAR(F17) -> 2012 | I17: =G17&"/"&H17 -> fevereiro/2012 | J17: =TEXT(F17,"dddd") -> terça-feira | K17: =VLOOKUP(A17,RELACIONAMENTOS!A:C,2,0) -> ATOTAL | L17: =VLOOKUP(A17,RELACIONAMENTOS!A:C,3,0) -> Simone | M17: =VLOOKUP(B17,RELACIONAMENTOS!E:F,2,0) -> João | N17: =VLOOKUP(B17,RELACIONAMENTOS!H:I,2,0) -> Daniel | O17: =VLOOKUP(A17,RELACIONAMENTOS!K:L,2,0) -> 78912345678 | P17: =VLOOKUP(B17,RELACIONAMENTOS!N:O,2,0) -> 90 | Q17: =IF(E17>500,"Meta atingida","Não atingida") -> Não atingida | R17: =IF(C17>300,"Meta atingida","Não atingida") -> Não atingida | S17: =IF(OR(Q17="Meta atingida",R17="Meta atingida"), "Sim","Não") -> Não | T17: =IF(AND(Q17="Meta atingida",R17="Meta atingida"), "Sim","Não") -> Não | U17: =IF(E17>=500,0,VLOOKUP(B17,RELACIONAMENTOS!N:O,2,0)) -> 90 | V17: =IF(E17<=200,1%,IF(E17<=400,2%,IF(E17<=600,3%,IF(E17<=800,4%,IF(E17<=1000,5%,IF(E17<=1800,10%,15%)))))) -> 0.02 | W17: =VLOOKUP(E17,RELACIONAMENTOS!$Q$1:$S$11,3,1) -> 0.02
A18: Dorflex | B18: CENTRO-OESTE | C18: 203 | D18: 3.5 | E18: =C18*D18 -> 710.5 | F18: 40959 | G18: =TEXT(F18,"mmmm") -> fevereiro | H18: =YEAR(F18) -> 2012 | I18: =G18&"/"&H18 -> fevereiro/2012 | J18: =TEXT(F18,"dddd") -> segunda-feira | K18: =VLOOKUP(A18,RELACIONAMENTOS!A:C,2,0) -> ATOTAL | L18: =VLOOKUP(A18,RELACIONAMENTOS!A:C,3,0) -> Simone | M18: =VLOOKUP(B18,RELACIONAMENTOS!E:F,2,0) -> João | N18: =VLOOKUP(B18,RELACIONAMENTOS!H:I,2,0) -> Daniel | O18: =VLOOKUP(A18,RELACIONAMENTOS!K:L,2,0) -> 78912345678 | P18: =VLOOKUP(B18,RELACIONAMENTOS!N:O,2,0) -> 90 | Q18: =IF(E18>500,"Meta atingida","Não atingida") -> Meta atingida | R18: =IF(C18>300,"Meta atingida","Não atingida") -> Não atingida | S18: =IF(OR(Q18="Meta atingida",R18="Meta atingida"), "Sim","Não") -> Sim | T18: =IF(AND(Q18="Meta atingida",R18="Meta atingida"), "Sim","Não") -> Não | U18: =IF(E18>=500,0,VLOOKUP(B18,RELACIONAMENTOS!N:O,2,0)) -> 0 | V18: =IF(E18<=200,1%,IF(E18<=400,2%,IF(E18<=600,3%,IF(E18<=800,4%,IF(E18<=1000,5%,IF(E18<=1800,10%,15%)))))) -> 0.04 | W18: =VLOOKUP(E18,RELACIONAMENTOS!$Q$1:$S$11,3,1) -> 0.04
A19: Dorflex | B19: CENTRO-OESTE | C19: 100 | D19: 3.5 | E19: =C19*D19 -> 350 | F19: 40958 | G19: =TEXT(F19,"mmmm") -> fevereiro | H19: =YEAR(F19) -> 2012 | I19: =G19&"/"&H19 -> fevereiro/2012 | J19: =TEXT(F19,"dddd") -> domingo | K19: =VLOOKUP(A19,RELACIONAMENTOS!A:C,2,0) -> ATOTAL | L19: =VLOOKUP(A19,RELACIONAMENTOS!A:C,3,0) -> Simone | M19: =VLOOKUP(B19,RELACIONAMENTOS!E:F,2,0) -> João | N19: =VLOOKUP(B19,RELACIONAMENTOS!H:I,2,0) -> Daniel | O19: =VLOOKUP(A19,RELACIONAMENTOS!K:L,2,0) -> 78912345678 | P19: =VLOOKUP(B19,RELACIONAMENTOS!N:O,2,0) -> 90 | Q19: =IF(E19>500,"Meta atingida","Não atingida") -> Não atingida | R19: =IF(C19>300,"Meta atingida","Não atingida") -> Não atingida | S19: =IF(OR(Q19="Meta atingida",R19="Meta atingida"), "Sim","Não") -> Não | T19: =IF(AND(Q19="Meta atingida",R19="Meta atingida"), "Sim","Não") -> Não | U19: =IF(E19>=500,0,VLOOKUP(B19,RELACIONAMENTOS!N:O,2,0)) -> 90 | V19: =IF(E19<=200,1%,IF(E19<=400,2%,IF(E19<=600,3%,IF(E19<=800,4%,IF(E19<=1000,5%,IF(E19<=1800,10%,15%)))))) -> 0.02 | W19: =VLOOKUP(E19,RELACIONAMENTOS!$Q$1:$S$11,3,1) -> 0.02
A20: Dorflex | B20: CENTRO-OESTE | C20: 10 | D20: 3 | E20: =C20*D20 -> 30 | F20: 40957 | G20: =TEXT(F20,"mmmm") -> fevereiro | H20: =YEAR(F20) -> 2012 | I20: =G20&"/"&H20 -> fevereiro/2012 | J20: =TEXT(F20,"dddd") -> sábado | K20: =VLOOKUP(A20,RELACIONAMENTOS!A:C,2,0) -> ATOTAL | L20: =VLOOKUP(A20,RELACIONAMENTOS!A:C,3,0) -> Simone | M20: =VLOOKUP(B20,RELACIONAMENTOS!E:F,2,0) -> João | N20: =VLOOKUP(B20,RELACIONAMENTOS!H:I,2,0) -> Daniel | O20: =VLOOKUP(A20,RELACIONAMENTOS!K:L,2,0) -> 78912345678 | P20: =VLOOKUP(B20,RELACIONAMENTOS!N:O,2,0) -> 90 | Q20: =IF(E20>500,"Meta atingida","Não atingida") -> Não atingida | R20: =IF(C20>300,"Meta atingida","Não atingida") -> Não atingida | S20: =IF(OR(Q20="Meta atingida",R20="Meta atingida"), "Sim","Não") -> Não | T20: =IF(AND(Q20="Meta atingida",R20="Meta atingida"), "Sim","Não") -> Não | U20: =IF(E20>=500,0,VLOOKUP(B20,RELACIONAMENTOS!N:O,2,0)) -> 90 | V20: =IF(E20<=200,1%,IF(E20<=400,2%,IF(E20<=600,3%,IF(E20<=800,4%,IF(E20<=1000,5%,IF(E20<=1800,10%,15%)))))) -> 0.01 | W20: =VLOOKUP(E20,RELACIONAMENTOS!$Q$1:$S$11,3,1) -> 0.01
... A92: Neosa | B92: SUL | C92: 102 | D92: 1 | E92: =C92*D92 -> 102 | F92: 40885 | G92: =TEXT(F92,"mmmm") -> dezembro | H92: =YEAR(F92) -> 2011 | I92: =G92&"/"&H92 -> dezembro/2011 | J92: =TEXT(F92,"dddd") -> quinta-feira | K92: =VLOOKUP(A92,RELACIONAMENTOS!A:C,2,0) -> Coopercarga | L92: =VLOOKUP(A92,RELACIONAMENTOS!A:C,3,0) -> Fernando | M92: =VLOOKUP(B92,RELACIONAMENTOS!E:F,2,0) -> João | N92: =VLOOKUP(B92,RELACIONAMENTOS!H:I,2,0) -> Tatiane | O92: =VLOOKUP(A92,RELACIONAMENTOS!K:L,2,0) -> 7891234567 | P92: =VLOOKUP(B92,RELACIONAMENTOS!N:O,2,0) -> 230 | Q92: =IF(E92>500,"Meta atingida","Não atingida") -> Não atingida | R92: =IF(C92>300,"Meta atingida","Não atingida") -> Não atingida | S92: =IF(OR(Q92="Meta atingida",R92="Meta atingida"), "Sim","Não") -> Não | T92: =IF(AND(Q92="Meta atingida",R92="Meta atingida"), "Sim","Não") -> Não | U92: =IF(E92>=500,0,VLOOKUP(B92,RELACIONAMENTOS!N:O,2,0)) -> 230 | V92: =IF(E92<=200,1%,IF(E92<=400,2%,IF(E92<=600,3%,IF(E92<=800,4%,IF(E92<=1000,5%,IF(E92<=1800,10%,15%)))))) -> 0.01 | W92: =VLOOKUP(E92,RELACIONAMENTOS!$Q$1:$S$11,3,1) -> 0.01

Sheet Fórmulas Básicas
C7: Valor de Venda | D7: Qtde
B8: Valor máximo (MAX) | C8: =MAX('Dados de Vendas'!E:E) -> 1470 | D8: =MAX('Dados de Vendas'!C:C) -> 600
B9: Valor Mínimo (MIN) | C9: =MIN('Dados de Vendas'!E:E) -> 30 | D9: =MIN('Dados de Vendas'!C:C) -> 10
B10: Valor médio (AVERAGE) | C10: =AVERAGE('Dados de Vendas'!E:E) -> 464.26923 | D10: =AVERAGE('Dados de Vendas'!C:C) -> 170.20879

Sheet RELACIONAMENTOS
A1: Produto | B1: Fabricante | C1: Gerente | E1: Regiao | F1: Supervisor | H1: Regiao | I1: Gerente 2 | K1: Produto | L1: código de barras | N1: Região | O1: Frete | Q1: VALOR DE VENDA MÍNIMO | R1: VALOR DE VENDAMÁXIMO | S1: COMISSÃO
A2: Neosa | B2: Coopercarga | C2: Fernando | E2: CENTRO-OESTE | F2: João | H2: CENTRO-OESTE | I2: Daniel | K2: tylenol | L2: 789123456 | N2: CENTRO-OESTE | O2: 90 | Q2: 0 | R2: 200 | S2: 0.01
A3: Dorflex | B3: ATOTAL | C3: Simone | E3: NORDESTE | F3: Maria | H3: NORDESTE | I3: Raquel | K3: Neosa | L3: 7891234567 | N3: NORDESTE | O3: 150 | Q3: =R2+1 -> 201 | R3: =Q3+199 -> 400 | S3: 0.02
A4: Tylenol | B4: ABC REMÉDIOS | C4: Talita | E4: SUL | F4: João | H4: SUL | I4: Tatiane | K4: dorflex | L4: 78912345678 | N4: SUL | O4: 230 | Q4: =R3+1 -> 401 | R4: =Q4+199 -> 600 | S4: 0.03
E5: SUDESTE | F5: Maria | H5: SUDESTE | I5: Thais | N5: SUDESTE | O5: 100 | Q5: =R4+1 -> 601 | R5: =Q5+199 -> 800 | S5: 0.04
Q6: =R5+1 -> 801 | R6: =Q6+199 -> 1000 | S6: 0.05
Q7: =R6+1 -> 1001 | R7: =Q7+199 -> 1200 | S7: 0.06
Q8: =R7+1 -> 1201 | R8: =Q8+199 -> 1400 | S8: 0.07
Q9: =R8+1 -> 1401 | R9: =Q9+199 -> 1600 | S9: 0.08
Q10: =R9+1 -> 1601 | R10: =Q10+199 -> 1800 | S10: 0.09
Q11: =R10+1 -> 1801 | R11: MAIORES QUE R$ 1.801,00 | S11: 0.1
Q13: VALOR A SER TESTADO | R13: COMISSÃO
Q14: 801 | R14: =VLOOKUP(Q14,Q2:S11,3,TRUE) -> 0.05

Sheet SE - IDADES
A1: NOME | B1: IDADE | C1: CLASSIFICAÇÃO: MAIOR OU MENOR DE IDADE
A2: JOÃO | B2: 10 | C2: =IF(B2>=18,"Maior de Idade","Menor de Idade") -> Menor de Idade
A3: PEDRO | B3: 15 | C3: =IF(B3>=18,"Maior de Idade","Menor de Idade") -> Menor de Idade
A4: JOSÉ | B4: 17 | C4: =IF(B4>=18,"Maior de Idade","Menor de Idade") -> Menor de Idade
A5: MARIA | B5: 18 | C5: =IF(B5>=18,"Maior de Idade","Menor de Idade") -> Maior de Idade
A6: SILVIA | B6: 19 | C6: =IF(B6>=18,"Maior de Idade","Menor de Idade") -> Maior de Idade
A7: ADÃO | B7: 18 | C7: =IF(B7>=18,"Maior de Idade","Menor de Idade") -> Maior de Idade
A8: EVA | B8: 16 | C8: =IF(B8>=18,"Maior de Idade","Menor de Idade") -> Menor de Idade

Sheet PROCV 1
A1: CÓDIGOS DE BARRA | B1: NOME DO PRODUTO | C1: PREÇO | G1: CÓDIGO DE BARRAS | H1: NOME DO PRODUTO | I1: PREÇO
A2: 78900000 | B2: =VLOOKUP(A2,G:I,2,0) -> Flanela | C2: =VLOOKUP(B2,H:J,2,0) -> 1.5 | G2: 12341234 | H2: Álcool | I2: 1
A3: 12343051 | B3: =VLOOKUP(A3,G:I,2,0) -> Amaciante | C3: =VLOOKUP(B3,H:J,2,0) -> 4 | G3: 12341452 | H3: Cera | I3: 4
A4: 12341634 | B4: =VLOOKUP(A4,G:I,2,0) -> Esponja | C4: =VLOOKUP(B4,H:J,2,0) -> 0.5 | G4: 12341525 | H4: Desinfetante | I4: 3
A5: 12341852 | B5: =VLOOKUP(A5,G:I,2,0) -> Guardanapo | C5: =VLOOKUP(B5,H:J,2,0) -> 1.65 | G5: 12341634 | H5: Esponja | I5: 0.5
A6: VALOR TOTAL | C6: =SUM(C2:C5) -> 7.65 | G6: 78900000 | H6: Flanela | I6: 1.5
G7: 12341852 | H7: Guardanapo | I7: 1.65
G8: 12341961 | H8: Limpa prata | I8: 5
G9: 12342070 | H9: Pano de chão | I9: 4
G10: 12342179 | H10: Papel Toalha | I10: 3.85
G11: 12342288 | H11: Purificador de ar | I11: 30
D12: PROCV | G12: 12342397 | H12: Sabão de coco | I12: 1.5
D13: VLOOKUP | G13: 12342506 | H13: Sabão em pasta | I13: 1.5
G14: 12342615 | H14: Sacos de lixo | I14: 7
G15: 12342724 | H15: Vanish | I15: 8
G16: 12342833 | H16: Amoníaco | I16: 5
G17: 12342942 | H17: Bombril | I17: 1.2
G18: 12343051 | H18: Amaciante | I18: 4
G19: 12343160 | H19: Detergente | I19: 1.4
G20: 12343269 | H20: Filtro de papel | I20: 2.5
G21: 12343378 | H21: Fósforo | I21: 2.1
G22: 12343487 | H22: Lâmpada | I22: 0.99
G23: 12343596 | H23: Palitos | I23: 1.5
G24: 12343705 | H24: Papel alumínio | I24: 4.5
G25: 12343814 | H25: Passe bem | I25: 4.5
... G144: 12356785 | H144: Tomate | I144: 2

Sheet CONTAR E SOMAR COM CONDIÇÕES
B7: COUNTA | C7: Contar quantidade total de registros de venda | F7: Exercícios adicionais
B8: CONT.VALORES | C8: =COUNTA('Dados de Vendas'!A2:A92) -> 91
B10: COUNTIF | C10: Contar registros de venda da região SUL | F10: COUNTIF | G10: Contar registros de venda do Dorflex
B11: CONT.SE | C11: =COUNTIF('Dados de Vendas'!B2:B92,"SUL") -> 30 | F11: CONT.SE | G11: =COUNTIF('Dados de Vendas'!A:A,"Dorflex") -> 36
B13: COUNTIFS | C13: Contar registros de venda da produto TYLENOL na região SUL | F13: COUNTIFS | G13: Contar registros de venda do TYLENOL do supervisor João
B14: CONT.SES | C14: =COUNTIFS('Dados de Vendas'!A:A,"Tylenol",'Dados de Vendas'!B:B,"SUL") -> 21 | F14: CONT.SES | G14: =COUNTIFS('Dados de Vendas'!A:A,"Tylenol",'Dados de Vendas'!M:M,"João") -> 21
B16: SUMIF | C16: ="Somar valores de vendas da região "&B18 -> Somar valores de vendas da região CENTRO-OESTE | F16: SUMIF | G16: Somar as QUANTIDADES vendidas do Produto Selecionado
B17: SOMASE | C17: =SUMIF('Dados de Vendas'!B2:B92,'CONTAR E SOMAR COM CONDIÇÕES'!B18,'Dados de Vendas'!E2:E92) -> 15612.5 | F17: SOMASE | G17: =SUMIF('Dados de Vendas'!A:A,'CONTAR E SOMAR COM CONDIÇÕES'!F18,'Dados de Vendas'!C:C) -> 6079
B18: CENTRO-OESTE | F18: Dorflex
B20: SUMIFS | C20: ="Somar valores de venda da região "&B22&" e do produto "&B23 -> Somar valores de venda da região CENTRO-OESTE e do produto Dorflex | F20: SUMIFS | G20: Somar as QUANTIDADES do Gerente e Produto Selecionados
B21: SOMASES | C21: =SUMIFS('Dados de Vendas'!E2:E92,'Dados de Vendas'!B2:B92,'CONTAR E SOMAR COM CONDIÇÕES'!B22,'Dados de Vendas'!A2:A92,'CONTAR E SOMAR COM CONDIÇÕES'!B23) -> 15612.5 | F21: SOMASES | G21: =SUMIFS('Dados de Vendas'!C:C,'Dados de Vendas'!L:L,'CONTAR E SOMAR COM CONDIÇÕES'!F22,'Dados de Vendas'!A:A,'CONTAR E SOMAR COM CONDIÇÕES'!F23) -> 6079
A22: REGIÃO | B22: CENTRO-OESTE | E22: GERENTE | F22: Simone
A23: PRODUTO | B23: Dorflex | E23: PRODUTO | F23: Dorflex
B25: COUNTIF | C25: Contar quantidades > 500
B26: CONT.SE | C26: =COUNTIF('Dados de Vendas'!C2:C92,">500") -> 1
B28: COUNTIF | C28: ="Contar quantidades > do que "&B30 -> Contar quantidades > do que 400
B29: CONT.SE | C29: =COUNTIF('Dados de Vendas'!C2:C92,">"&B30) -> 6
B30: 400
B32: COUNTIF | C32: Contar registros posteriores a 1/1/12
B33: CONT.SE | C33: =COUNTIF('Dados de Vendas'!F2:F92,">01/01/12") -> 65
B35: COUNTIF | C35: CONTAR VENDAS REALIZADAS NO DIA 01/01/2012
B36: CONT.SE | C36: =COUNTIF('Dados de Vendas'!F2:F92,"1/1/12") -> 1

Sheet REGIÕES
A1: CENTRO-OESTE | H1: Dorflex
A2: NORDESTE | H2: Neosa
A3: SUDESTE | H3: Tylenol
A4: SUL

Sheet PROTEÇÃO DE PLANILHAS
A1: PRODUTO | B1: QUANTIDADE | C1: VALOR UNIÁRIO | D1: VALOR TOTAL
A2: A | C2: 2 | D2: =C2*B2 -> 0
A3: B | C3: 3 | D3: =C3*B3 -> 0
A4: C | C4: 4 | D4: =C4*B4 -> 0
A5: D | C5: 5 | D5: =C5*B5 -> 0

Sheet AUDITORIA DE FÓRMULAS
A1: Investimentos em Propaganda
A2: Produto | B2: Revista | E2: Produto | F2: Jornal | I2: Produto | J2: Internet
A3: A | B3: 1200 | E3: B | F3: 2500 | I3: A | J3: 3000
A4: B | B4: 1500 | E4: F | F4: 1000 | I4: B | J4: 3500
A5: C | B5: 1000 | E5: A | F5: 400 | I5: G | J5: 6000
A6: D | B6: 200 | E6: E | F6: 200 | I6: E | J6: 1000
A10: Selecione o Produto | E10: Gasto Total
A11: A | E11: =VLOOKUP(A11,A3:B6,2,FALSE)+VLOOKUP(A11,E3:F6,2,FALSE)+VLOOKUP(A11,I3:J6,2,FALSE) -> 4600

Sheet JANELA DE INSPEÇÃO
B1: Valor total + R$1.000,00
B2: ='AUDITORIA DE FÓRMULAS'!E11+1000 -> 5600
B3: ='AUDITORIA DE FÓRMULAS'!E11+1000 -> 5600
